LICENSE.txt
MANIFEST.in
README.txt
setup.py
pcart_newsblog/__init__.py
pcart_newsblog/admin.py
pcart_newsblog/apps.py
pcart_newsblog/cms_apps.py
pcart_newsblog/cms_plugins.py
pcart_newsblog/forms.py
pcart_newsblog/models.py
pcart_newsblog/urls.py
pcart_newsblog/views.py
pcart_newsblog.egg-info/PKG-INFO
pcart_newsblog.egg-info/SOURCES.txt
pcart_newsblog.egg-info/dependency_links.txt
pcart_newsblog.egg-info/not-zip-safe
pcart_newsblog.egg-info/requires.txt
pcart_newsblog.egg-info/top_level.txt
pcart_newsblog/migrations/0001_initial.py
pcart_newsblog/migrations/__init__.py
pcart_newsblog/templates/newsblog/article.html
pcart_newsblog/templates/newsblog/articles.html
pcart_newsblog/templates/newsblog/plugins/article_block.html
pcart_newsblog/templates/newsblog/plugins/default_article_block.html